{
  "title": "台灣全民財務健康知識測驗",
  "description": "測試您對台灣財務健康現況的了解程度",
  "total_questions": 12,
  "categories": [
    "基礎知識",
    "退休規劃",
    "風險管理",
    "生涯規劃",
    "理財目標",
    "投資知識",
    "理財原則",
    "家庭理財",
    "財務規劃",
    "緊急預備金",
    "金融素養",
    "理財教育"
  ],
  "questions": [
    {
      "id": 1,
      "question": "根據國泰世華2023年調查，台灣人財務健康平均分數是多少？",
      "options": [
        "A. 55.2分",
        "B. 59.2分",
        "C. 62.8分",
        "D. 66.3分"
      ],
      "correct": "B",
      "explanation": "根據國泰世華銀行《2023臺灣全民財務健康關鍵報告》，台灣人財務健康平均分數為59.2分，屬於「普通」等級。",
      "category": "基礎知識"
    },
    {
      "id": 2,
      "question": "台灣人認為至少需要準備多少退休金才能安心退休？",
      "options": [
        "A. 1000萬元",
        "B. 1200萬元",
        "C. 1431萬元",
        "D. 1600萬元"
      ],
      "correct": "C",
      "explanation": "調查顯示，國人認為至少要準備1431萬元才能退休，且退休後每月生活費約需5萬元。",
      "category": "退休規劃"
    },
    {
      "id": 3,
      "question": "在財務健康五大構面中，台灣人表現最佳的是哪一項？",
      "options": [
        "A. 財務規劃",
        "B. 風險抵抗力",
        "C. 財務信心",
        "D. 心理富足程度"
      ],
      "correct": "B",
      "explanation": "根據調查，台灣人在「風險抵抗力」構面表現最佳，近5成民眾的儲蓄水位可支應6個月以上的基本生活所需。",
      "category": "風險管理"
    },
    {
      "id": 4,
      "question": "哪個年齡層被認為是台灣民眾財務健康狀態的重要分水嶺？",
      "options": [
        "A. 35-39歲",
        "B. 40-44歲",
        "C. 45-49歲",
        "D. 50-54歲"
      ],
      "correct": "C",
      "explanation": "45-49歲為台灣民眾財務健康狀態的重要分水嶺，平均達61.1分，因為此年齡層面臨多重財務壓力。",
      "category": "生涯規劃"
    },
    {
      "id": 5,
      "question": "台灣人最主要的理財目標是什麼？",
      "options": [
        "A. 買房",
        "B. 旅遊",
        "C. 退休金準備",
        "D. 子女教育基金"
      ],
      "correct": "C",
      "explanation": "近6成民眾將「退休」列為財務目標，但其中卻有超過5成沒有實際財務規劃。",
      "category": "理財目標"
    },
    {
      "id": 6,
      "question": "根據調查，台灣人最偏好的理財工具是什麼？",
      "options": [
        "A. 股票",
        "B. 台幣存款",
        "C. 保險",
        "D. ETF"
      ],
      "correct": "B",
      "explanation": "台幣存款(59.4%)是台灣人最主要的理財工具，其次是定存(45.8%)和股票(43.0%)。",
      "category": "投資知識"
    },
    {
      "id": 7,
      "question": "強化財務健康的三大關鍵不包括以下哪一項？",
      "options": [
        "A. 計畫",
        "B. 紀律",
        "C. 技能",
        "D. 運氣"
      ],
      "correct": "D",
      "explanation": "國泰世華歸納出強化財務健康的3大關鍵：計畫、紀律、技能。運氣不是可控制的因素。",
      "category": "理財原則"
    },
    {
      "id": 8,
      "question": "有子女者與無子女者的財務健康狀態差異如何？",
      "options": [
        "A. 有子女者明顯較差",
        "B. 無子女者明顯較好",
        "C. 沒有明顯差異",
        "D. 因人而異"
      ],
      "correct": "C",
      "explanation": "調查發現有子女者在財務健康狀態與無子女者並無明顯差異，破除了「教養孩子易拖垮財務」的迷思。",
      "category": "家庭理財"
    },
    {
      "id": 9,
      "question": "台灣民眾在財務規劃方面最大的問題是什麼？",
      "options": [
        "A. 收入太低",
        "B. 支出太高",
        "C. 超過3成未設立財務目標",
        "D. 投資知識不足"
      ],
      "correct": "C",
      "explanation": "逾3成民眾過去一年未設立財務目標，更有超過2成民眾無定期檢視財務規劃的習慣。",
      "category": "財務規劃"
    },
    {
      "id": 10,
      "question": "根據調查，多少比例的台灣民眾儲蓄水位可支應6個月以上的基本生活所需？",
      "options": [
        "A. 約3成",
        "B. 約4成",
        "C. 近5成",
        "D. 超過6成"
      ],
      "correct": "C",
      "explanation": "近5成民眾的儲蓄水位可支應6個月以上的基本生活所需，這在「風險抵抗力」構面獲得高分。",
      "category": "緊急預備金"
    },
    {
      "id": 11,
      "question": "台灣金融素養程度高的碩士以上學歷民眾比例約為多少？",
      "options": [
        "A. 不到5%",
        "B. 約10%",
        "C. 約15%",
        "D. 超過20%"
      ],
      "correct": "A",
      "explanation": "根據2024年調查，碩士以上自認金融素養程度高的民眾不到5%，顯示高學歷族群的金融素養未必比較高。",
      "category": "金融素養"
    },
    {
      "id": 12,
      "question": "理財教育應該從什麼時候開始？",
      "options": [
        "A. 大學階段",
        "B. 出社會工作後",
        "C. 中小學階段",
        "D. 退休前"
      ],
      "correct": "C",
      "explanation": "理財教育應該從中小學階段開始，建立良好的財務健康體質，才能成功達成財務目標。",
      "category": "理財教育"
    }
  ],
  "scoring": {
    "excellent": {
      "min": 90,
      "max": 100,
      "description": "您具備優秀的財務健康知識，是理財高手！"
    },
    "good": {
      "min": 70,
      "max": 89,
      "description": "您的財務健康知識良好，但仍有進步空間。"
    },
    "average": {
      "min": 50,
      "max": 69,
      "description": "您的財務健康知識一般，建議多加學習。"
    },
    "poor": {
      "min": 0,
      "max": 49,
      "description": "您的財務健康知識需要大幅提升，建議參加理財教育課程。"
    }
  }
}